parse_rest/__init__.py
parse_rest/config.py
parse_rest/connection.py
parse_rest/core.py
parse_rest/datatypes.py
parse_rest/installation.py
parse_rest/query.py
parse_rest/role.py
parse_rest/test_relations.py
parse_rest/tests.py
parse_rest/user.py
parse_rest/cloudcode/cloud/main.js
qs_parse_rest-0.2.20240920.dist-info/COPYING
qs_parse_rest-0.2.20240920.dist-info/METADATA
qs_parse_rest-0.2.20240920.dist-info/WHEEL
qs_parse_rest-0.2.20240920.dist-info/top_level.txt
qs_parse_rest-0.2.20240920.dist-info/RECORD
