Metadata-Version: 2.1
Name: qs-parse-rest
Version: 0.2.20240920
Summary: A client library for Parse.com'.s REST API
Home-page: https://github.com/milesrichardson/ParsePy
Maintainer: Miles Richardson
Maintainer-email: miles.richardson@gmail.com
Classifier: Development Status :: 4 - Beta
Classifier: Environment :: Web Environment
Classifier: Intended Audience :: Developers
Classifier: License :: OSI Approved :: GNU General Public License v3 (GPLv3)
Classifier: Operating System :: OS Independent
Classifier: Programming Language :: Python :: 2.6
Classifier: Programming Language :: Python :: 2.7
Classifier: Programming Language :: Python :: 3.3
Classifier: Programming Language :: Python :: 3.4
Classifier: Programming Language :: Python :: 3.12
License-File: COPYING
Requires-Dist: six
